tyclonielogger/__init__.py
TyclonieLogger-2.0.dist-info/METADATA
TyclonieLogger-2.0.dist-info/WHEEL
TyclonieLogger-2.0.dist-info/top_level.txt
TyclonieLogger-2.0.dist-info/RECORD
