Metadata-Version: 2.1
Name: TyclonieLogger
Version: 2.0
Summary: A library designed to make logging easy.
Home-page: UNKNOWN
Author: Tyclonie
License: MIT
Platform: UNKNOWN
Requires-Dist: colorama (==0.4.6)
